subfolder/__init__.py
avcalculator-0.1.dist-info/LICENSE.txt
avcalculator-0.1.dist-info/METADATA
avcalculator-0.1.dist-info/WHEEL
avcalculator-0.1.dist-info/top_level.txt
avcalculator-0.1.dist-info/RECORD
