Metadata-Version: 2.1
Name: avcalculator
Version: 0.1
Summary: <Basic desc>
Home-page: UNKNOWN
Author: AV
Author-email: av@gmail.com
License: UNKNOWN
Platform: UNKNOWN
Classifier: Programming Language :: Python :: 3
Classifier: License :: OSI Approved :: MIT License
Classifier: Operating System :: OS Independent
